{
  "positions": {
    "A1": "bird",
    "A2": "tvmonitor",
    "A3": "chair",
    "A4": "person",
    "A5": "cat",
    "A6": "cow",
    "B1": "boat",
    "B2": "bicycle",
    "B3": "boat",
    "B4": "dog",
    "B5": "bicycle",
    "B6": "bottle",
    "C1": "cat",
    "C2": "diningtable",
    "C3": "chair",
    "C4": "dog",
    "C5": "person",
    "C6": "tvmonitor",
    "D1": "aeroplane",
    "D2": "cow",
    "D3": "pottedplant",
    "D4": "bottle",
    "D5": "car",
    "D6": "bird",
    "E1": "aeroplane",
    "E2": "sofa",
    "E3": "sofa",
    "E4": "diningtable",
    "E5": "pottedplant",
    "E6": "car"
  }
}
